indevolt_api/__init__.py
indevolt_api/client.py
indevolt_api-1.1.0.dist-info/licenses/LICENSE
indevolt_api-1.1.0.dist-info/METADATA
indevolt_api-1.1.0.dist-info/WHEEL
indevolt_api-1.1.0.dist-info/top_level.txt
indevolt_api-1.1.0.dist-info/RECORD
