Metadata-Version: 2.4
Name: indevolt-api
Version: 1.1.0
Summary: Python API client for Indevolt devices
Author: A. Gideonse
License: MIT
Project-URL: Homepage, https://github.com/xirtnl/indevolt-api
Project-URL: Repository, https://github.com/xirtnl/indevolt-api
Project-URL: Issues, https://github.com/xirtnl/indevolt-api/issues
Keywords: indevolt,api,async,aiohttp
Classifier: Development Status :: 5 - Production/Stable
Classifier: Intended Audience :: Developers
Classifier: License :: OSI Approved :: MIT License
Classifier: Operating System :: OS Independent
Classifier: Programming Language :: Python :: 3
Classifier: Programming Language :: Python :: 3.11
Classifier: Programming Language :: Python :: 3.12
Classifier: Programming Language :: Python :: 3.13
Classifier: Topic :: System :: Hardware
Classifier: Typing :: Typed
Requires-Python: >=3.11
License-File: LICENSE
Requires-Dist: aiohttp>=3.9.0
Dynamic: license-file
